HybridSuperQubits/__init__.py
HybridSuperQubits/andreev.py
HybridSuperQubits/ferbo.py
HybridSuperQubits/fluxonium.py
HybridSuperQubits/gatemon.py
HybridSuperQubits/gatemonium.py
HybridSuperQubits/jja.py
HybridSuperQubits/operators.py
HybridSuperQubits/qubit_base.py
HybridSuperQubits/resonator.py
HybridSuperQubits/storage.py
HybridSuperQubits/utilities.py
hybridsuperqubits-0.9.3.dist-info/LICENSE
hybridsuperqubits-0.9.3.dist-info/METADATA
hybridsuperqubits-0.9.3.dist-info/WHEEL
hybridsuperqubits-0.9.3.dist-info/RECORD
