Metadata-Version: 2.3
Name: HybridSuperQubits
Version: 0.9.3
Summary: Package to simulate hybrid superconducting qubits
License: MIT
Author: Joan Cáceres
Author-email: contact@joancaceres.com
Requires-Python: >=3.10,<3.14
Classifier: License :: OSI Approved :: MIT License
Classifier: Programming Language :: Python :: 3
Classifier: Programming Language :: Python :: 3.10
Classifier: Programming Language :: Python :: 3.11
Classifier: Programming Language :: Python :: 3.12
Classifier: Programming Language :: Python :: 3.13
Provides-Extra: full
Provides-Extra: qutip
Provides-Extra: scientific
Requires-Dist: matplotlib (>=3.8)
Requires-Dist: numpy (>=1.26) ; extra == "full" or extra == "scientific"
Requires-Dist: qutip (>=5.1) ; extra == "full" or extra == "qutip"
Requires-Dist: scipy (>=1.5) ; extra == "full" or extra == "scientific"
Requires-Dist: scqubits (>=4.3) ; extra == "full" or extra == "qutip"
Requires-Dist: tqdm (>=4.66)
Project-URL: Documentation, https://hybridsuperqubits.readthedocs.io
Project-URL: Homepage, https://github.com/joanjcaceres/HybridSuperQubits
Project-URL: Repository, https://github.com/joanjcaceres/HybridSuperQubits
